{
    "homo": {
        "name": "Home",
        "type": "town",
        "number": 1,
        "data_people": [
            {
                "name": "father",
                "age": 45,
                "gender": "man",
                "job": "engineer"
            },
            {
                "name": "mother",
                "age": 42,
                "gender": "woman",
                "job": "teacher"
            },
            {
                "name": "me",
                "age": 19,
                "gender": "man",
                "job": "student"
            }
        ]
    },
    "hospital": {
        "name": "hospital",
        "type": "town",
        "number": 2,
        "data_people": [
            {
                "name": "jack",
                "age": 30,
                "gender": "man",
                "job": "doctor"
            },
            {
                "name": "tom",
                "age": 20,
                "gender": "man",
                "job": "doctor"
            },
            {
                "name": "jane",
                "age": 25,
                "gender": "woman",
                "job": "nurse"
            },
            {
                "name": "mary",
                "age": 22,
                "gender": "woman",
                "job": "nurse"
            },
            {
                "name": "lily",
                "age": 21,
                "gender": "woman",
                "job": "nurse"
            }
        ]
    }
}